hesabe/__init__.py
hesabe/checkout.py
hesabe/crypt.py
hesabe_test_checkout-0.0.5.dist-info/METADATA
hesabe_test_checkout-0.0.5.dist-info/WHEEL
hesabe_test_checkout-0.0.5.dist-info/top_level.txt
hesabe_test_checkout-0.0.5.dist-info/RECORD
