Metadata-Version: 2.1
Name: hesabe-test-checkout
Version: 0.0.5
Summary: checkout test package
Home-page: UNKNOWN
Author: KL
Author-email: sounak.karmaalab@gmail.com
License: UNKNOWN
Keywords: python,django,hesabe
Platform: UNKNOWN
Classifier: Development Status :: 1 - Planning
Classifier: Intended Audience :: Developers
Classifier: Programming Language :: Python :: 3
Classifier: Operating System :: Unix
Classifier: Operating System :: MacOS :: MacOS X
Classifier: Operating System :: Microsoft :: Windows
Requires-Dist: requests
Requires-Dist: pycryptodome
